LICENSE
MANIFEST.in
README.md
requirements.txt
setup.py
Bdrl/__init__.py
Bdrl/__main__.py
Bdrl/config.py
Bdrl/logging.py
Bdrl/version.py
Bdrl/helpers/PyroHelpers.py
Bdrl/helpers/__init__.py
Bdrl/helpers/adminHelpers.py
Bdrl/helpers/basic.py
Bdrl/helpers/expand.py
Bdrl/helpers/interval.py
Bdrl/helpers/misc.py
Bdrl/helpers/msg_types.py
Bdrl/helpers/parser.py
Bdrl/helpers/tools.py
Bdrl/helpers/utility.py
Bdrl/helpers/sql/__init__.py
Bdrl/helpers/sql/afk_sql.py
Bdrl/helpers/sql/cloner_db.py
Bdrl/helpers/sql/filters_sql.py
Bdrl/helpers/sql/gban_sql.py
Bdrl/helpers/sql/globals.py
Bdrl/helpers/sql/gmute_sql.py
Bdrl/helpers/sql/no_log_pms_sql.py
Bdrl/helpers/sql/notes_sql.py
Bdrl/helpers/sql/pm_db.py
Bdrl/helpers/sql/pm_permit_sql.py
Bdrl/helpers/sql/pmstuff.py
Bdrl/helpers/sql/welcome_sql.py
Bdrl/image/__init__.py
Bdrl/image/bdrl.jpg
Bdrl/plugins/__init__.py
Bdrl/plugins/admins.py
Bdrl/plugins/afk.py
Bdrl/plugins/animation.py
Bdrl/plugins/asupan.py
Bdrl/plugins/broadcast.py
Bdrl/plugins/clone.py
Bdrl/plugins/create.py
Bdrl/plugins/devs.py
Bdrl/plugins/extras.py
Bdrl/plugins/fakeaction.py
Bdrl/plugins/globals.py
Bdrl/plugins/help.py
Bdrl/plugins/heroku.py
Bdrl/plugins/info.py
Bdrl/plugins/locks.py
Bdrl/plugins/logger.py
Bdrl/plugins/members.py
Bdrl/plugins/misc.py
Bdrl/plugins/notes.py
Bdrl/plugins/nyolong.py
Bdrl/plugins/pmpermit.py
Bdrl/plugins/prefix.py
Bdrl/plugins/profile.py
Bdrl/plugins/purge.py
Bdrl/plugins/spam.py
Bdrl/plugins/stats.py
Bdrl/plugins/stickers.py
Bdrl/plugins/sys.py
Bdrl/plugins/updater.py
Bdrl/plugins/vctools.py
Bdrl/utils/__init__.py
Bdrl/utils/help_formatting.py
Bdrl/utils/misc.py
Bdrl/utils/pastebin.py
Bdrl/utils/sections.py
Bdrl/utils/tools.py
Bdrl/utils/core/bdrl.png
Bdrl/utils/core/default.ttf
Yanto.egg-info/PKG-INFO
Yanto.egg-info/SOURCES.txt
Yanto.egg-info/dependency_links.txt
Yanto.egg-info/not-zip-safe
Yanto.egg-info/requires.txt
Yanto.egg-info/top_level.txt